seres.py
sino.py
sino-0.0.3.dist-info/METADATA
sino-0.0.3.dist-info/WHEEL
sino-0.0.3.dist-info/entry_points.txt
sino-0.0.3.dist-info/top_level.txt
sino-0.0.3.dist-info/RECORD
