Metadata-Version: 2.1
Name: sino
Version: 0.0.3
Requires-Dist: click
